pytest_culprit/__init__.py
pytest_culprit/cli.py
pytest_culprit-0.1.0.dist-info/licenses/LICENSE
pytest_culprit-0.1.0.dist-info/METADATA
pytest_culprit-0.1.0.dist-info/WHEEL
pytest_culprit-0.1.0.dist-info/entry_points.txt
pytest_culprit-0.1.0.dist-info/top_level.txt
pytest_culprit-0.1.0.dist-info/RECORD
