Metadata-Version: 2.4
Name: pytest-culprit
Version: 0.1.0
Summary: Find the last Git commit where a pytest test started failing
Author-email: Vishal Teotia <vashuteotia123@gmail.com>
License: MIT
Requires-Python: >=3.7
License-File: LICENSE
Dynamic: license-file
